{
    "backgroundColor": "rgba(255,255,255,0)",
    "title": {
        "textStyle": {
            "color": "#373b4d"
        },
        "subtextStyle": {
            "color": "#616b7c"
        }
    },
    "bar": {
        "itemStyle": {
            "barBorderColor": "#ccc"
        }
    },
    "categoryAxis": {
        "axisLine": {
            "lineStyle": {
                "color": "#6E7079"
            }
        },
        "axisTick": {
            "lineStyle": {
                "color": "#6E7079"
            }
        },
        "axisLabel": {
            "color": "#6E7079"
        }
    },
    "valueAxis": {
        "axisLabel": {
            "color": "#6E7079"
        },
        "splitLine": {
            "lineStyle": {
                "color": ["#E8E9F0"]
            }
        }
    },
    "logAxis": {
        "axisLine": {
            "lineStyle": {
                "color": "#6E7079"
            }
        },
        "axisTick": {
            "lineStyle": {
                "color": "#6E7079"
            }
        },
        "axisLabel": {
            "color": "#6E7079"
        },
        "splitLine": {
            "lineStyle": {
                "color": ["#E0E6F1"]
            }
        }
    },
    "timeAxis": {
        "axisLine": {
            "lineStyle": {
                "color": "#6E7079"
            }
        },
        "axisTick": {
            "lineStyle": {
                "color": "#6E7079"
            }
        },
        "axisLabel": {
            "color": "#6E7079"
        },
        "splitLine": {
            "lineStyle": {
                "color": ["#E0E6F1"]
            }
        }
    },
    "toolbox": {
        "iconStyle": {
            "borderColor": "#999"
        },
        "emphasis": {
            "iconStyle": {
                "borderColor": "#666"
            }
        }
    },
    "legend": {
        "textStyle": {
            "color": "#333"
        }
    },
    "tooltip": {
        "axisPointer": {
            "lineStyle": {
                "color": "#ccc"
            },
            "crossStyle": {
                "color": "#ccc"
            }
        }
    },
    "timeline": {
        "lineStyle": {
            "color": "#DAE1F5"
        },
        "itemStyle": {
            "color": "#A4B1D7"
        },
        "controlStyle": {
            "color": "#A4B1D7",
            "borderColor": "#A4B1D7"
        },
        "checkpointStyle": {
            "color": "#316bf3",
            "borderColor": "#fff"
        },
        "label": {
            "color": "#A4B1D7"
        },
        "emphasis": {
            "itemStyle": {
                "color": "#FFF"
            },
            "controlStyle": {
                "color": "#A4B1D7",
                "borderColor": "#A4B1D7"
            },
            "label": {
                "color": "#A4B1D7"
            }
        }
    },
    "visualMap": {
        "color": ["#bf444c", "#d88273", "#f6efa6"]
    },
    "markPoint": {
        "label": {
            "color": "#eee"
        },
        "emphasis": {
            "label": {
                "color": "#eee"
            }
        }
    }
}
